rm_trash/LICENSE.md
rm_trash/__init__.py
rm_trash/commands.py
rm_trash/trash.py
rm_trash-1.0.2.dist-info/entry_points.txt
rm_trash-1.0.2.dist-info/LICENSE.md
rm_trash-1.0.2.dist-info/METADATA
rm_trash-1.0.2.dist-info/WHEEL
rm_trash-1.0.2.dist-info/RECORD
