Metadata-Version: 2.1
Name: rm-trash
Version: 1.0.2
Summary: 🗑 Safe(r) deletion of files from the macOS command line
Home-page: https://github.com/celsiusnarhwal/rm-trash
Author: celsius narhwal
Author-email: hello@celsiusnarhwal.dev
Requires-Python: >=3.8,<4.0
Classifier: Programming Language :: Python :: 3
Classifier: Programming Language :: Python :: 3.8
Classifier: Programming Language :: Python :: 3.9
Classifier: Programming Language :: Python :: 3.10
Classifier: Programming Language :: Python :: 3.11
Requires-Dist: inflect (>=6.0.2,<7.0.0)
Requires-Dist: typer[all] (>=0.7.0,<0.8.0)
